osm2rail/__init__.py
osm2rail/classes.py
osm2rail/download_by_BBBike.py
osm2rail/download_by_Geofabrik.py
osm2rail/download_by_Overpass.py
osm2rail/network.py
osm2rail/plotter.py
osm2rail/reader.py
osm2rail/settings.py
osm2rail/utils.py
osm2rail/web.py
osm2rail/writer.py
osm2rail/dat/BBBike-cities-coordinates.pickle
osm2rail/dat/BBBike-cities.pickle
osm2rail/dat/BBBike-download-dictionary.pickle
osm2rail/dat/BBBike-subregion-catalogue.pickle
osm2rail/dat/BBBike-subregion-name-list.pickle
osm2rail/dat/Geofabrik-continent-subregions.pickle
osm2rail/dat/Geofabrik-downloads-catalogue.pickle
osm2rail/dat/Geofabrik-index-of-all-downloads.pickle
osm2rail/dat/Geofabrik-region-subregion-tier.pickle
osm2rail/dat/Geofabrik-subregion-name-list.pickle
osm2rail-0.0.6.dist-info/METADATA
osm2rail-0.0.6.dist-info/RECORD
osm2rail-0.0.6.dist-info/WHEEL
osm2rail-0.0.6.dist-info/top_level.txt
