Metadata-Version: 2.1
Name: osm2rail
Version: 0.0.6
Summary: An open-source education tool for constructing modeling datasets of railway transportation
Home-page: https://github.com/PariseC/osm2rail
Author: Jiawei Lu, Qian Fu, Zanyang Cui, Dr.Junhua Chen
Author-email: jiaweil9@asu.edu, q.fu@bham.ac.uk, zanyangcui@outlook.com, cjh@bjtu.edu.cn
License: Apache License 2.0
Platform: UNKNOWN
Classifier: License :: OSI Approved :: Apache Software License
Classifier: Programming Language :: Python :: 3
Requires-Python: >=3.6.0
Requires-Dist: bs4
Requires-Dist: matplotlib
Requires-Dist: osmium
Requires-Dist: fuzzywuzzy
Requires-Dist: shapely
Requires-Dist: pandas
Requires-Dist: numpy
Requires-Dist: requests
